pyaddons/__init__.py
pyaddons-0.1.1.dist-info/LICENSE
pyaddons-0.1.1.dist-info/METADATA
pyaddons-0.1.1.dist-info/WHEEL
pyaddons-0.1.1.dist-info/top_level.txt
pyaddons-0.1.1.dist-info/RECORD
