Metadata-Version: 2.1
Name: pyaddons
Version: 0.1.1
Summary: A collection of addons for the Python programming language
Home-page: https://github.com/matt-hu/pyaddons
Author: Matt H
Author-email: matt.hu1@outlook.com
License: UNKNOWN
Platform: UNKNOWN
Classifier: Programming Language :: Python :: 3
Classifier: License :: OSI Approved :: GNU General Public License v3 (GPLv3)
Classifier: Operating System :: OS Independent
Requires-Python: >=3.6
